{
    "about": "紹介",
    "aboutDescription": "ゲームページで主題歌を再生する",
    "aboutLabel": "ゲームの主題歌について",
    "backupOverrides": "Backup overrides",
    "backupOverridesLabel": "Backup all overrides",
    "backupSuccessful": "Backup successful",
    "backupSuccessfulDetails": "Overrides have been backed up.",
    "changeThemeMusic": "主題歌を変える",
    "close": "Close",
    "defaultMuted": "デフォルトミュート",
    "defaultMutedDescription": "手動設置で主題歌を再生する",
    "deleteDownloads": "Delete downloads",
    "deleteDownloadsConfirm": "Are you sure you want to delete all downloaded music?",
    "deleteDownloadsDescription": "Delete all downloaded music. This will not reset overrides.",
    "deleteDownloadsLabel": "Delete all downloads",
    "deleteOverrides": "オーバーライドを削除",
    "deleteOverridesConfirm": "Are you sure you want to delete all overrides?",
    "deleteOverridesDescription": "This will also delete all backups of your overrides!",
    "deleteOverridesLabel": "全てのオーバーライドを削除する",
    "download": "Download",
    "downloadAudio": "Download Music",
    "downloadAudioDescription": "Download selected music instead of streaming it. Only applies to newly made selections.",
    "downloadFailed": "Download failed",
    "downloadFailedDetail": "Could not download this music.",
    "downloadRestoreSuccessful": "Downloads successful",
    "downloadRestoreSuccessfulDetails": "All missing songs have been downloaded.",
    "extras": "Extras",
    "gameSettings": "ゲーム設定",
    "gameVolumeDescription": "ゲームのため、主題歌を調整する",
    "helpTranslate": "Help translate",
    "invidiousInstance": "Invidious Instance",
    "invidiousInstanceDescription": "Which Invidious instance would you like to use for searching and getting audio?",
    "noMusicLabel": "音楽なし",
    "overrides": "オーバーライド",
    "play": "再生",
    "reset": "Reset",
    "resetVolume": "リセット",
    "restoreDownloads": "Restore downloads",
    "restoreDownloadsConfirm": "Download all missing songs?",
    "restoreDownloadsConfirmDescription": "This will download up to {num} songs and might take a while.",
    "restoreDownloadsDescription": "Download all songs from manually set overrides that haven't been downloaded yet.",
    "restoreDownloadsLabel": "Restore missing downloads",
    "restoreDownloadsOperation": "Downloading {current}/{total}...",
    "restoreDownloadsOperationTitle": "Downloading missing songs...",
    "restoreOverrides": "Select backup",
    "restoreOverridesConfirm": "Restore this backup?",
    "restoreOverridesConfirmDetails": "This will overwrite all your current overrides!",
    "restoreOverridesLabel": "Restore overrides from backup",
    "restoreSuccessful": "Restore successful",
    "restoreSuccessfulDetails": "Overrides have been restored from backup.",
    "search": "検索",
    "select": "選択",
    "selected": "したした",
    "settings": "設定",
    "showQrCode": "Show QR Code",
    "stop": "中止",
    "supportDescription": "スチームデック自作の ディスコードdeckbrew.xyz/discordを訪ねる",
    "supportLabel": "サポート",
    "useYtDlp": "Use yt-dlp",
    "useYtDlpDescription": "Access YouTube directly without Invidious",
    "volume": "音量",
    "volumeDescription": "音量調整"
}